seose.py
seo_sentinel-1.0.2.dist-info/licenses/LICENSE
seo_sentinel-1.0.2.dist-info/METADATA
seo_sentinel-1.0.2.dist-info/WHEEL
seo_sentinel-1.0.2.dist-info/entry_points.txt
seo_sentinel-1.0.2.dist-info/top_level.txt
seo_sentinel-1.0.2.dist-info/RECORD
