Metadata-Version: 2.4
Name: seo-sentinel
Version: 1.0.2
Summary: SEO Sentinel is a comprehensive automated SEO auditing tool that crawls websites, detects SEO issues, and generates detailed HTML reports for website optimization.
Author-email: Nayan Das <nayanchandradas@hotmail.com>
Maintainer-email: Nayan Das <nayanchandradas@hotmail.com>
License-Expression: MIT
Project-URL: Homepage, https://github.com/nayandas69/SEO-Sentinel
Project-URL: Repository, https://github.com/nayandas69/SEO-Sentinel
Project-URL: Documentation, https://github.com/nayandas69/SEO-Sentinel#readme
Project-URL: Issues, https://github.com/nayandas69/SEO-Sentinel/issues
Project-URL: Changelog, https://github.com/nayandas69/SEO-Sentinel/releases
Project-URL: Bug Reports, https://github.com/nayandas69/SEO-Sentinel/issues
Project-URL: Feature Requests, https://github.com/nayandas69/SEO-Sentinel/issues
Project-URL: Discord, https://discord.gg/skHyssu
Project-URL: Author Website, https://nayandas69.github.io/link-in-bio
Keywords: seo,crawler,auditor,website-analysis,python,seo-sentinel,web-scraping,performance-analysis,metadata-analysis
Classifier: Development Status :: 5 - Production/Stable
Classifier: Intended Audience :: Developers
Classifier: Intended Audience :: End Users/Desktop
Classifier: Operating System :: OS Independent
Classifier: Programming Language :: Python :: 3
Classifier: Programming Language :: Python :: 3.8
Classifier: Programming Language :: Python :: 3.9
Classifier: Programming Language :: Python :: 3.10
Classifier: Programming Language :: Python :: 3.11
Classifier: Programming Language :: Python :: 3.12
Classifier: Topic :: Internet :: WWW/HTTP :: Indexing/Search
Classifier: Topic :: Software Development :: Libraries :: Python Modules
Classifier: Topic :: Utilities
Classifier: Environment :: Console
Classifier: Natural Language :: English
Requires-Python: >=3.8
License-File: LICENSE
Requires-Dist: beautifulsoup4<5.0.0,>=4.12.0
Requires-Dist: requests<3.0.0,>=2.31.0
Requires-Dist: tqdm<5.0.0,>=4.65.0
Requires-Dist: jinja2<4.0.0,>=3.1.0
Requires-Dist: urllib3<3.0.0,>=1.26.0
Provides-Extra: dev
Requires-Dist: pytest>=7.0.0; extra == "dev"
Requires-Dist: black>=23.0.0; extra == "dev"
Provides-Extra: performance
Requires-Dist: aiohttp>=3.8.0; extra == "performance"
Requires-Dist: asyncio>=3.4.3; extra == "performance"
Provides-Extra: export
Requires-Dist: pandas>=1.5.0; extra == "export"
Requires-Dist: openpyxl>=3.1.0; extra == "export"
Dynamic: license-file
